openctmpy/__init__.py
openctmpy/compression.py
openctmpy/ctm.py
openctmpy/header.py
openctmpy/reader.py
openctmpy/utils.py
openctmpy/version.py
openctmpy/writer.py
tests/__init__.py
tests/test_basic.py
python_openctm_nightly-1.1.1.dist-info/LICENSE
python_openctm_nightly-1.1.1.dist-info/METADATA
python_openctm_nightly-1.1.1.dist-info/WHEEL
python_openctm_nightly-1.1.1.dist-info/top_level.txt
python_openctm_nightly-1.1.1.dist-info/RECORD
