Metadata-Version: 2.1
Name: python-openctm-nightly
Version: 1.1.1
Summary: Pure Python Interface for the OpenCTM File Format (nightly)
Home-page: https://github.com/lejafar/python-openctm
Author: Rafael Hautekiet
Author-email: rafaelhautekiet@gmail.com
License: zlib License
Platform: UNKNOWN
Classifier: Programming Language :: Python :: 2.7
Classifier: Programming Language :: Python :: 3.4
Classifier: Programming Language :: Python :: 3.5
Classifier: Programming Language :: Python :: 3.6
Classifier: Programming Language :: Python :: 3.7
Classifier: Natural Language :: English
Classifier: Topic :: Scientific/Engineering
Classifier: License :: OSI Approved :: zlib/libpng License
Classifier: Operating System :: OS Independent
Requires-Dist: numpy (>=1.14.2)
